{"mCombination":{"mNumbers":[{"mAdditionalNumber":-1,"mIsAdditionalNumber":false,"arrayNumbers":{"23":1},"mostValid":23,"mostValidOccurenceCount":1,"secondValid":-1,"secondValidOccurenceCount":0},{"mAdditionalNumber":-1,"mIsAdditionalNumber":false,"arrayNumbers":{"24":1},"mostValid":24,"mostValidOccurenceCount":1,"secondValid":-1,"secondValidOccurenceCount":0},{"mAdditionalNumber":-1,"mIsAdditionalNumber":false,"arrayNumbers":{"26":1},"mostValid":26,"mostValidOccurenceCount":1,"secondValid":-1,"secondValidOccurenceCount":0},{"mAdditionalNumber":-1,"mIsAdditionalNumber":false,"arrayNumbers":{"28":1},"mostValid":28,"mostValidOccurenceCount":1,"secondValid":-1,"secondValidOccurenceCount":0},{"mAdditionalNumber":-1,"mIsAdditionalNumber":false,"arrayNumbers":{"33":1},"mostValid":33,"mostValidOccurenceCount":1,"secondValid":-1,"secondValidOccurenceCount":0},{"mAdditionalNumber":-1,"mIsAdditionalNumber":false,"arrayNumbers":{"37":1},"mostValid":37,"mostValidOccurenceCount":1,"secondValid":-1,"secondValidOccurenceCount":0},{"mAdditionalNumber":-1,"mIsAdditionalNumber":false,"arrayNumbers":{"38":1},"mostValid":38,"mostValidOccurenceCount":1,"secondValid":-1,"secondValidOccurenceCount":0},null,null,null,null,null,null,null,null,null,null],"mAdditonalNumbers":[{"mAdditionalNumber":34,"mIsAdditionalNumber":true,"arrayNumbers":{},"mostValid":-1,"mostValidOccurenceCount":0,"secondValid":-1,"secondValidOccurenceCount":0}],"mCombinationIdNumber":0,"mIsValid":false,"mActiveNumbers":7},"mDate":"Apr 4, 2012 12:00:00 AM","mResultDetails":{"mResultDetails":{"6+1":{"mType":"6+1","mLocations":"Škofljica","mOcurrance":1,"mAmount":7706.32},"3+1":{"mType":"3+1","mLocations":"\u0026nbsp;","mOcurrance":8579,"mAmount":2.91},"7":{"mType":"7","mLocations":"\u0026nbsp;","mOcurrance":0,"mAmount":46237.94},"6":{"mType":"6","mLocations":"\u0026nbsp;","mOcurrance":23,"mAmount":670.11},"5":{"mType":"5","mLocations":"\u0026nbsp;","mOcurrance":670,"mAmount":48.88},"4":{"mType":"4","mLocations":"\u0026nbsp;","mOcurrance":9662,"mAmount":6.77}}},"mStoreId":0,"mNumber":28}